Metadata-Version: 2.1
Name: d365
Version: 0.1.1
Summary: A python library to make Dynamics 365 integrations easier
Home-page: https://github.com/dyvision/d365-py
Author: Dyvision
Author-email: the.dyvision@gmail.com
License: MIT
Platform: UNKNOWN
Classifier: Programming Language :: Python :: 3
Classifier: Programming Language :: Python :: 3.4
Classifier: Programming Language :: Python :: 3.5
